hbf/dataclean/laundry.py
hbf/hbfmain.py
hbf/helpers/logtofile.py
hbf/preprocess/buildaddress.py
hbf/preprocess/buildsearchbox.py
hbf/preprocess/getinput.py
hbf/scrape/buildzillowsearchpageurl.py
hbf/scrape/gethtml.py
hbf/scrape/getzillowurls.py
hbf/scrape/list2frame.py
hbf/scrape/scrapehomeurls.py
hbf/scrape/scrapepagecount.py
hbf/scrape/scraperesultcount.py
hbf/scrape/scrapezillowdata.py
hbf/tests/hbf.inp
hbf/tests/test_buildaddress.py
hbf/tests/test_buildsearchbox.py
hbf/tests/test_buildzillowsearchpageurl.py
hbf/tests/test_scrapehomeurls.py
hbf/tests/test_scrapepagecount.py
hbf/tests/test_scraperesultcount.py
hbf/tests/test_scrapezillowdata.py
hbf-0.1.2.dist-info/LICENSE
hbf-0.1.2.dist-info/WHEEL
hbf-0.1.2.dist-info/METADATA
hbf-0.1.2.dist-info/RECORD
