Metadata-Version: 2.1
Name: hbf
Version: 0.1.2
Summary: A program to predict a home's sell price using data scraped from the internet
License: GPL-3.0-only
Author: Your Name
Author-email: you@example.com
Requires-Python: >=3.7,<4.0
Classifier: License :: OSI Approved :: GNU General Public License v3 (GPLv3)
Classifier: Programming Language :: Python :: 3
Classifier: Programming Language :: Python :: 3.7
Classifier: Programming Language :: Python :: 3.8
Classifier: Programming Language :: Python :: 3.9
Requires-Dist: beautifulsoup4 (>=4.9.3,<5.0.0)
Requires-Dist: configparser (>=5.0.0,<6.0.0)
Requires-Dist: geopy (>=2.0.0,<3.0.0)
Requires-Dist: numpy (==1.19.3)
Requires-Dist: pandas (>=1.1.3,<2.0.0)
Requires-Dist: progress (>=1.5,<2.0)
Requires-Dist: requests (>=2.24.0,<3.0.0)
